dakara_feeder/__init__.py
dakara_feeder/__main__.py
dakara_feeder/customization.py
dakara_feeder/difference.py
dakara_feeder/directory.py
dakara_feeder/json.py
dakara_feeder/metadata.py
dakara_feeder/similarity.py
dakara_feeder/song.py
dakara_feeder/utils.py
dakara_feeder/version.py
dakara_feeder/web_client.py
dakara_feeder/yaml.py
dakara_feeder/feeder/__init__.py
dakara_feeder/feeder/songs.py
dakara_feeder/feeder/tags.py
dakara_feeder/feeder/work_types.py
dakara_feeder/feeder/works.py
dakara_feeder/resources/__init__.py
dakara_feeder/resources/feeder.yaml
dakara_feeder/subtitle/__init__.py
dakara_feeder/subtitle/extraction.py
dakara_feeder/subtitle/parsing.py
dakarafeeder-1.9.0.dist-info/LICENSE
dakarafeeder-1.9.0.dist-info/METADATA
dakarafeeder-1.9.0.dist-info/WHEEL
dakarafeeder-1.9.0.dist-info/entry_points.txt
dakarafeeder-1.9.0.dist-info/top_level.txt
dakarafeeder-1.9.0.dist-info/RECORD
