Metadata-Version: 2.2
Name: dakarafeeder
Version: 1.9.0
Summary: External database feeder for the Dakara Project
Author-email: Flore <flore.love@gmail.com>, Neraste <neraste.herr10@gmail.com>
License: MIT License
Project-URL: Homepage, https://github.com/DakaraProject/dakara-feeder
Project-URL: Repository, https://github.com/DakaraProject/dakara-feeder.git
Project-URL: Issues, https://github.com/DakaraProject/dakara-feeder/issues
Project-URL: Changelog, https://github.com/DakaraProject/dakara-feeder/blob/master/CHANGELOG.md
Classifier: License :: OSI Approved :: MIT License
Classifier: Programming Language :: Python
Classifier: Programming Language :: Python :: 3
Classifier: Programming Language :: Python :: 3.9
Classifier: Programming Language :: Python :: 3.10
Classifier: Programming Language :: Python :: 3.11
Classifier: Programming Language :: Python :: 3.12
Classifier: Programming Language :: Python :: 3.13
Classifier: Operating System :: OS Independent
Classifier: Environment :: Console
Classifier: Intended Audience :: Developers
Requires-Python: >=3.9
License-File: LICENSE
Requires-Dist: dakarabase<2.2.0,>=2.1.0
Requires-Dist: filetype<1.3.0,>=1.2.0
Requires-Dist: packaging<25.0,>=24.2
Requires-Dist: pymediainfo<7.1.0,>=7.0.1
Requires-Dist: pysubs2<1.9.0,>=1.8.0
Provides-Extra: dev
Requires-Dist: black<25.2.0,>=25.1.0; extra == "dev"
Requires-Dist: codecov<2.2.0,>=2.1.13; extra == "dev"
Requires-Dist: isort<6.1.0,>=6.0.0; extra == "dev"
Requires-Dist: pdoc<15.2.0,>=15.0.1; extra == "dev"
Requires-Dist: pre-commit<4.2.0,>=4.1.0; extra == "dev"
Requires-Dist: pytest-cov<6.1.0,>=6.0.0; extra == "dev"
Requires-Dist: pytest<8.4.0,>=8.3.4; extra == "dev"
Requires-Dist: ruff<0.10.0,>=0.9.6; extra == "dev"
